kani/ext/ratelimits/__init__.py
kani/ext/ratelimits/engine.py
kani_ratelimits-1.0.1.dist-info/METADATA
kani_ratelimits-1.0.1.dist-info/WHEEL
kani_ratelimits-1.0.1.dist-info/licenses/LICENSE
kani_ratelimits-1.0.1.dist-info/RECORD
