Metadata-Version: 2.3
Name: kani-ratelimits
Version: 1.0.1
Summary: A wrapper engine to enforce request-based, token-based, and concurrency-based limits on kani engines.
Project-URL: Homepage, https://github.com/zhudotexe/kani-ratelimits
Project-URL: Bug Tracker, https://github.com/zhudotexe/kani-ratelimits/issues
Author-email: Andrew Zhu <andrew@zhu.codes>
License: MIT License
License-File: LICENSE
Classifier: Development Status :: 5 - Production/Stable
Classifier: Intended Audience :: Science/Research
Classifier: License :: OSI Approved :: MIT License
Classifier: Operating System :: OS Independent
Classifier: Programming Language :: Python :: 3
Classifier: Topic :: Scientific/Engineering :: Artificial Intelligence
Requires-Python: >=3.10
Requires-Dist: aiolimiter<2.0.0,>=1.0.0
Requires-Dist: kani<2.0.0,>=1.0.0rc0
